math_evaluator/__init__.py
math_evaluator/explicit.py
math_evaluator/implicit.py
math_evaluator-0.0.3.dist-info/LICENSE
math_evaluator-0.0.3.dist-info/METADATA
math_evaluator-0.0.3.dist-info/WHEEL
math_evaluator-0.0.3.dist-info/top_level.txt
math_evaluator-0.0.3.dist-info/RECORD
