Metadata-Version: 2.1
Name: math-evaluator
Version: 0.0.3
Summary: A package that evaluates a mathematical expression given as a string.
Author-email: Rashid Harvey <rashid.harvey@fu-berlin.de>
Project-URL: Homepage, https://github.com/theRealProHacker/MathEvaluator
Project-URL: Bug Tracker, https://github.com/theRealProHacker/MathEvaluator/issues
Classifier: Programming Language :: Python :: 3
Classifier: License :: OSI Approved :: MIT License
Classifier: Operating System :: OS Independent
Requires-Python: >=3.7
License-File: LICENSE
